sofapy/__init__.py
sofapy/cli.py
sofapy/client.py
sofapy/exceptions.py
sofapy/logger.py
sofapy/models.py
sofapy-0.1.1.dist-info/licenses/LICENSE
sofapy-0.1.1.dist-info/METADATA
sofapy-0.1.1.dist-info/WHEEL
sofapy-0.1.1.dist-info/entry_points.txt
sofapy-0.1.1.dist-info/top_level.txt
sofapy-0.1.1.dist-info/RECORD
