Metadata-Version: 2.4
Name: sofapy
Version: 0.1.1
Summary: A python wrapper of MacAdmins SOFA (sofa.macadmins.io)
Author-email: Andrew Lerman <info@liquidzoo.io>
License:                                  Apache License
Project-URL: Repository, https://github.com/liquidz00/sofapy
Project-URL: Issues, https://github.com/liquidz00/sofapy/issues/new
Keywords: SOFA,MacAdmins,CVE,macOS
Requires-Python: >=3.12
License-File: LICENSE
Requires-Dist: asyncclick>=8.3.0.7
Requires-Dist: httpx>=0.28.1
Requires-Dist: pydantic>=2.12.5
Provides-Extra: dev
Requires-Dist: faker>=38.2.0; extra == "dev"
Requires-Dist: pre-commit>=4.5.0; extra == "dev"
Requires-Dist: pytest>=9.0.2; extra == "dev"
Requires-Dist: pytest-asyncio>=1.3.0; extra == "dev"
Requires-Dist: pytest-cov>=7.0.0; extra == "dev"
Requires-Dist: ruff>=0.14.9; extra == "dev"
Dynamic: license-file
